dexodus_perps_sdk/__init__.py
dexodus_perps_sdk/automationOrdersAbi.js
dexodus_perps_sdk/dexodusAbi.js
dexodus_perps_sdk/index.js
dexodus_perps_sdk/markets.js
dexodus_perps_sdk/runner.js
dexodus_perps_sdk/examples/example_python.py
dexodus_perps_sdk/examples/test_python_wrapper.py
dexodus_perps_sdk-1.1.1.dist-info/licenses/LICENSE
dexodus_perps_sdk-1.1.1.dist-info/METADATA
dexodus_perps_sdk-1.1.1.dist-info/WHEEL
dexodus_perps_sdk-1.1.1.dist-info/top_level.txt
dexodus_perps_sdk-1.1.1.dist-info/RECORD
