Metadata-Version: 2.4
Name: dexodus-perps-sdk
Version: 1.1.1
Summary: Python SDK for Dexodus perpetual futures trading platform on Base
Home-page: https://github.com/dexodus/perps-sdk-python
Author: Dexodus Team
Author-email: Dexodus Team <dev@dexodus.com>
License: MIT
Project-URL: Homepage, https://github.com/dexodus/perps-sdk-python
Project-URL: Documentation, https://docs.dexodus.com/sdk
Requires-Python: >=3.7
License-File: LICENSE
Dynamic: author
Dynamic: home-page
Dynamic: license-file
Dynamic: requires-python
